cv_algorithms/__init__.py
cv_algorithms/_checks.py
cv_algorithms/_cv_algorithms.cpython-310-x86_64-linux-gnu.so
cv_algorithms/_ffi.py
cv_algorithms/classification.py
cv_algorithms/colorspace.py
cv_algorithms/contours.py
cv_algorithms/distance.py
cv_algorithms/grassfire.py
cv_algorithms/morphology.py
cv_algorithms/neighbours.py
cv_algorithms/popcount.py
cv_algorithms/resize.py
cv_algorithms/text.py
cv_algorithms/thinning.py
cv_algorithms/utils.py
cv_algorithms-1.1.1.dist-info/LICENSE
cv_algorithms-1.1.1.dist-info/METADATA
cv_algorithms-1.1.1.dist-info/WHEEL
cv_algorithms-1.1.1.dist-info/RECORD
