Metadata-Version: 2.1
Name: cv-algorithms
Version: 1.1.1
Summary: Optimized OpenCV extra algorithms for Python
License: Apache-2.0
Author: Uli Köhler
Author-email: github@techoverflow.net
Requires-Python: >=3.5,<4.0
Classifier: License :: OSI Approved :: Apache Software License
Classifier: Programming Language :: Python :: 3
Classifier: Programming Language :: Python :: 3.5
Classifier: Programming Language :: Python :: 3.6
Classifier: Programming Language :: Python :: 3.7
Classifier: Programming Language :: Python :: 3.8
Classifier: Programming Language :: Python :: 3.9
Classifier: Programming Language :: Python :: 3.10
Classifier: Programming Language :: Python :: 3.11
Classifier: Programming Language :: Python :: 3.12
Requires-Dist: cffi (>=0.7)
Requires-Dist: numpy
Requires-Dist: opencv-python
Requires-Dist: setuptools
